launchable_cli_args/__init__.py
launchable_cli_args/cli_args.py
launchable_cli_args/error_counter.py
launchable_cli_args/recordbuild.py
launchable_cli_args/recordsession.py
launchable_cli_args/recordtests.py
launchable_cli_args/subset.py
launchable_config/__init__.py
launchable_config/__main__.py
pytest_launchable/__init__.py
pytest_launchable/launchable_test_context.py
pytest_launchable/memorizer.py
yaml2obj/__init__.py
yaml2obj/loader.py
yaml2obj/writer.py
pytest_launchable-0.5.1.dist-info/LICENSE
pytest_launchable-0.5.1.dist-info/METADATA
pytest_launchable-0.5.1.dist-info/WHEEL
pytest_launchable-0.5.1.dist-info/entry_points.txt
pytest_launchable-0.5.1.dist-info/top_level.txt
pytest_launchable-0.5.1.dist-info/RECORD
