Metadata-Version: 2.1
Name: pytest-launchable
Version: 0.5.1
Summary: Launchable Pytest Plugin
Home-page: https://launchableinc.com/
Author: Launchable, Inc.
Author-email: info@launchableinc.com
License: Apache Software License v2
Classifier: Programming Language :: Python :: 3
Classifier: License :: OSI Approved :: Apache Software License
Classifier: Operating System :: OS Independent
Classifier: Framework :: Pytest
Requires-Python: >=3.7
License-File: LICENSE
Requires-Dist: pytest (>=4.2.0)
Requires-Dist: lxml
Requires-Dist: pyyaml
Requires-Dist: launchable
